MANIFEST.in
README.rst
requirements.txt
setup.cfg
setup.py
djmicrosip_generaventasconsig/__init__.py
djmicrosip_generaventasconsig/__init__.pyc
djmicrosip_generaventasconsig/config.pyc
djmicrosip_generaventasconsig/forms.pyc
djmicrosip_generaventasconsig/models.pyc
djmicrosip_generaventasconsig/urls.pyc
djmicrosip_generaventasconsig/views.pyc
djmicrosip_generaventasconsig.egg-info/PKG-INFO
djmicrosip_generaventasconsig.egg-info/SOURCES.txt
djmicrosip_generaventasconsig.egg-info/dependency_links.txt
djmicrosip_generaventasconsig.egg-info/requires.txt
djmicrosip_generaventasconsig.egg-info/top_level.txt
djmicrosip_generaventasconsig/static/djmicrosip_generaventasconsig/js/generar_ventas.js
djmicrosip_generaventasconsig/static/djmicrosip_generaventasconsig/js/preferencias.js
djmicrosip_generaventasconsig/templates/djmicrosip_generaventasconsig/base.html
djmicrosip_generaventasconsig/templates/djmicrosip_generaventasconsig/generar_ventas.html
djmicrosip_generaventasconsig/templates/djmicrosip_generaventasconsig/index.html
djmicrosip_generaventasconsig/templates/djmicrosip_generaventasconsig/preferencias.html